gcl_certbot_plugin/__init__.py
gcl_certbot_plugin/acme.py
gcl_certbot_plugin/clients.py
gcl_certbot_plugin/plugin.py
gcl_certbot_plugin/examples/create_cert.py
gcl_certbot_plugin/tests/__init__.py
gcl_certbot_plugin/tests/unit/__init__.py
gcl_certbot_plugin/tests/unit/test_basic.py
gcl_certbot_plugin-0.0.5.dist-info/licenses/AUTHORS
gcl_certbot_plugin-0.0.5.dist-info/licenses/LICENSE
gcl_certbot_plugin-0.0.5.dist-info/METADATA
gcl_certbot_plugin-0.0.5.dist-info/WHEEL
gcl_certbot_plugin-0.0.5.dist-info/entry_points.txt
gcl_certbot_plugin-0.0.5.dist-info/pbr.json
gcl_certbot_plugin-0.0.5.dist-info/top_level.txt
gcl_certbot_plugin-0.0.5.dist-info/RECORD
